README.md
setup.py
qtmodel/__init__.py
qtmodel.egg-info/PKG-INFO
qtmodel.egg-info/SOURCES.txt
qtmodel.egg-info/dependency_links.txt
qtmodel.egg-info/top_level.txt
qtmodel/core/__init__.py
qtmodel/core/data_helper.py
qtmodel/core/model_db.py
qtmodel/core/qt_server.py
qtmodel/core/result_db.py
qtmodel/mdb/__init__.py
qtmodel/mdb/mdb_analysis_setting.py
qtmodel/mdb/mdb_assistant.py
qtmodel/mdb/mdb_boundary.py
qtmodel/mdb/mdb_construction_stage.py
qtmodel/mdb/mdb_dynamic_load.py
qtmodel/mdb/mdb_live_load.py
qtmodel/mdb/mdb_load.py
qtmodel/mdb/mdb_project.py
qtmodel/mdb/mdb_property.py
qtmodel/mdb/mdb_section.py
qtmodel/mdb/mdb_sink_load.py
qtmodel/mdb/mdb_static_load.py
qtmodel/mdb/mdb_structure.py
qtmodel/mdb/mdb_temperature_load.py
qtmodel/mdb/mdb_tendon.py
qtmodel/odb/__init__.py
qtmodel/odb/odb_model_boundary.py
qtmodel/odb/odb_model_load.py
qtmodel/odb/odb_model_material.py
qtmodel/odb/odb_model_section.py
qtmodel/odb/odb_model_stage.py
qtmodel/odb/odb_model_structure.py
qtmodel/odb/odb_result_data.py
qtmodel/odb/odb_result_plot.py
qtmodel/odb/odb_view.py
test/test_model.py