Metadata-Version: 2.4
Name: qtmodel
Version: 2.1.2
Summary: python modeling for qt 2025-12-23 
Home-page: https://github.com/Inface0443/pyqt
Author: dqy-zhj
Author-email: 1105417715@qq.com
Classifier: License :: OSI Approved :: MIT License
Classifier: Programming Language :: Python :: 3
Classifier: Operating System :: OS Independent
Dynamic: author
Dynamic: author-email
Dynamic: classifier
Dynamic: description
Dynamic: description-content-type
Dynamic: home-page
Dynamic: summary
